{
  "generator-jhipster": {
    "promptValues": {
      "packageName": "com.lpa.jblog"
    },
    "jhipsterVersion": "4.10.2",
    "baseName": "jblog",
    "packageName": "com.lpa.jblog",
    "packageFolder": "com/lpa/jblog",
    "serverPort": "8080",
    "authenticationType": "jwt",
    "hibernateCache": "ehcache",
    "clusteredHttpSession": false,
    "websocket": false,
    "databaseType": "sql",
    "devDatabaseType": "h2Memory",
    "prodDatabaseType": "mysql",
    "searchEngine": false,
    "messageBroker": false,
    "serviceDiscoveryType": false,
    "buildTool": "maven",
    "enableSocialSignIn": false,
    "enableSwaggerCodegen": false,
    "jwtSecretKey": "9d9c01ebfe0326853fe907100808c233d14630cf",
    "clientFramework": "angularX",
    "useSass": false,
    "clientPackageManager": "yarn",
    "applicationType": "monolith",
    "testFrameworks": [],
    "jhiPrefix": "jhi",
    "enableTranslation": false
  }
}